[
  {
    "filament_weight": 750,
    "diameter": 1.75,
    "spool_refill": false,
    "empty_spool_weight": 165,
    "article_number": "HDGL-175BDBU-00750",
    "discontinued": false,
    "purchase_links": [
      {
        "store_id": "formfutura",
        "url": "https://www.formfutura.com/hdglass"
      }
    ]
  },
  {
    "filament_weight": 750,
    "diameter": 2.85,
    "spool_refill": false,
    "empty_spool_weight": 165,
    "article_number": "HDGL-285BDBU-00750",
    "discontinued": false,
    "purchase_links": [
      {
        "store_id": "formfutura",
        "url": "https://www.formfutura.com/hdglass"
      }
    ]
  }
]
