[
  {
    "uuid": "15321a7f-80fd-4c02-9e37-a03c17459257",
    "filament_weight": 750,
    "diameter": 1.75,
    "empty_spool_weight": 230
  },
  {
    "uuid": "e330ec5c-3462-45f3-b93f-302cc1f73d88",
    "filament_weight": 2500,
    "diameter": 1.75,
    "empty_spool_weight": 590
  },
  {
    "uuid": "3bd10b34-3bc8-4b7b-bbb9-e0f249f4aa11",
    "filament_weight": 750,
    "diameter": 2.85,
    "empty_spool_weight": 230
  },
  {
    "uuid": "f9e4217e-dac0-4469-a1ae-9e6db69676d4",
    "filament_weight": 2500,
    "diameter": 2.85,
    "empty_spool_weight": 590
  }
]
